hyaa/__init__.py
hyaa/main.py
hyaa-0.10.dist-info/METADATA
hyaa-0.10.dist-info/WHEEL
hyaa-0.10.dist-info/entry_points.txt
hyaa-0.10.dist-info/top_level.txt
hyaa-0.10.dist-info/RECORD
