Metadata-Version: 2.1
Name: hyaa
Version: 0.10
Summary: Hyaa 
Home-page: https://github.com/iam-bkpl/rasifal
Author: Kapil Bhandari
Author-email: iam.bkpl031@gmail.com
Classifier: Programming Language :: Python :: 3
Classifier: License :: OSI Approved :: MIT License
Classifier: Operating System :: OS Independent
Requires-Python: >=3.6
Requires-Dist: click
